tisane/INFERENCE.md
tisane/__init__.py
tisane/code_generator.py
tisane/concept.py
tisane/concept_graph.py
tisane/conceptual_model.py
tisane/data.py
tisane/design.py
tisane/docstring_helpers.py
tisane/effect_set.py
tisane/family.py
tisane/family_link_inference.py
tisane/graph.py
tisane/graph_inference.py
tisane/graph_vis_support.py
tisane/gui/README.md
tisane/gui/__init__.py
tisane/gui/assets/extra_styles.css
tisane/gui/callbacks.py
tisane/gui/default_explanations.json
tisane/gui/example.py
tisane/gui/example_inputs/main_interaction.json
tisane/gui/example_inputs/main_interaction_multiple_random_slopes.json
tisane/gui/example_inputs/main_interaction_random_intercept_slope_correlated.json
tisane/gui/example_inputs/main_interaction_random_intercepts.json
tisane/gui/example_inputs/main_interaction_random_slope_interaction.json
tisane/gui/example_inputs/main_interaction_random_slope_one_variable.json
tisane/gui/example_inputs/main_only.json
tisane/gui/family_link_function_callbacks.py
tisane/gui/family_link_functions.json
tisane/gui/generate_examples.py
tisane/gui/gui.py
tisane/gui/gui_components.py
tisane/gui/gui_helpers.py
tisane/gui/gui_strings.py
tisane/gui/random_effects_callbacks.py
tisane/gui/strings.json
tisane/level.py
tisane/main.py
tisane/random_effects.py
tisane/statistical_model.py
tisane/treatment.py
tisane/variable.py
tisane-0.1.0.dist-info/LICENSE
tisane-0.1.0.dist-info/WHEEL
tisane-0.1.0.dist-info/METADATA
tisane-0.1.0.dist-info/RECORD
