Metadata-Version: 2.1
Name: tisane
Version: 0.1.0
Summary: 
Author: Eunice Jun
Author-email: eunice.m.jun@gmail.com
Requires-Python: >=3.7.11,<4.0.0
Classifier: Programming Language :: Python :: 3
Classifier: Programming Language :: Python :: 3.10
Classifier: Programming Language :: Python :: 3.8
Classifier: Programming Language :: Python :: 3.9
Requires-Dist: Flask (>=1.1.2,<2.0.0)
Requires-Dist: Sphinx (>=4.1.2,<5.0.0)
Requires-Dist: coverage (>=5.5,<6.0)
Requires-Dist: dash (>=1.20.0,<2.0.0)
Requires-Dist: dash-bootstrap-components (>=0.12.0,<0.13.0)
Requires-Dist: dash-daq (>=0.5.0,<0.6.0)
Requires-Dist: h5 (>=0.4.1,<0.5.0)
Requires-Dist: h5py (==3.3.0)
Requires-Dist: ipykernel (>=6.3.1,<7.0.0)
Requires-Dist: jupyter (>=1.0.0,<2.0.0)
Requires-Dist: jupyter-dash (>=0.4.0,<0.5.0)
Requires-Dist: more-itertools (>=8.7.0,<9.0.0)
Requires-Dist: networkx (>=2.5.1,<3.0.0)
Requires-Dist: numpydoc (>=1.1.0,<2.0.0)
Requires-Dist: pandas (>=1.1.0,<2.0.0)
Requires-Dist: patsy (>=0.5.1,<0.6.0)
Requires-Dist: plotly (>=4.14.3,<5.0.0)
Requires-Dist: pydata-sphinx-theme (>=0.6.3,<0.7.0)
Requires-Dist: pydot (>=1.4.2,<2.0.0)
Requires-Dist: pymer4 (>=0.7.5,<0.8.0)
Requires-Dist: pytest (>=6.2.4,<7.0.0)
Requires-Dist: pytest-cov (>=2.11.1,<3.0.0)
Requires-Dist: sphinx-autoapi (>=1.8.4,<2.0.0)
Requires-Dist: statsmodels (>=0.12.2,<0.13.0)
Requires-Dist: toml (>=0.10.2,<0.11.0)
Requires-Dist: tweedie (>=0.0.7,<0.0.8)
